LICENSE
README.md
setup.py
MockMPI.egg-info/PKG-INFO
MockMPI.egg-info/SOURCES.txt
MockMPI.egg-info/dependency_links.txt
MockMPI.egg-info/requires.txt
MockMPI.egg-info/top_level.txt
mockmpi/__init__.py
mockmpi/_version.py
mockmpi/comm.py
mockmpi/exec.py
tests/test_args.py
tests/test_comm.py