Metadata-Version: 2.4
Name: MockMPI
Version: 0.8.3
Summary: A tool for mocking mpi4py for testing
Home-page: https://github.com/rmjarvis/MockMPI
Download-URL: https://github.com/rmjarvis/MockMPI/releases/tag/v0.8.3.zip
Author: Mike Jarvis and collaborators
Author-email: michael@jarvis.net
Keywords: MPI,development,unittesting
Classifier: Development Status :: 4 - Beta
Classifier: Intended Audience :: Developers
Classifier: License :: OSI Approved :: BSD License
Classifier: Programming Language :: Python :: 3
Requires-Python: >=3.5
License-File: LICENSE
Requires-Dist: numpy
Dynamic: author
Dynamic: author-email
Dynamic: classifier
Dynamic: description
Dynamic: description-content-type
Dynamic: download-url
Dynamic: home-page
Dynamic: keywords
Dynamic: license-file
Dynamic: requires-dist
Dynamic: requires-python
Dynamic: summary
